{
  "url": "https://rs.no/sikker-til-sjos/redningsvest-til-barn/",
  "site": "redningsselskapet",
  "source_id": "redningsselskapet_sjovett",
  "title": "Redningsvest til barn - Redningsselskapet",
  "status_code": 200,
  "content_type": "text/html; charset=UTF-8",
  "etag": null,
  "last_modified": null,
  "checksum_sha256": "3d07ac20220afb8bc3455813f8a1eb3316c9b8c8c10f0b59b2ad76a5edba4e78",
  "fetched_at": "2026-06-02T11:12:28.528050+00:00",
  "depth": 2,
  "text_chars": 7168,
  "n_links": 135,
  "n_pdf_links": 0,
  "n_images": 0,
  "images": [],
  "files": {
    "html": "pages/sikker-til-sjos-redningsvest-til-barn.html",
    "text": "pages/sikker-til-sjos-redningsvest-til-barn.txt"
  },
  "anchors": [
    {
      "level": 1,
      "text": "På utkikk etter redningsvest til barn?",
      "id": "main-content"
    },
    {
      "level": 2,
      "text": "Fant du det du lette etter?",
      "id": "gform_wrapper_15"
    }
  ]
}